{
  "id": "dependencies",
  "name": "Dependencies & Security",
  "version": "1.0.0",
  "tier": "community",
  "description": "Tracks Dependabot vulnerability alerts and license distribution across all repositories.",
  "widgets": [
    {
      "id": "vuln-summary",
      "type": "stat-card",
      "title": "Vulnerabilities",
      "description": "Total open Dependabot alerts broken down by severity: Critical, High, Medium, Low.",
      "defaultSize": "1/3",
      "tier": "community",
      "config": {
        "severity_weighting": {
          "type": "boolean",
          "label": "Custom severity weighting",
          "default": false,
          "tier": "pro"
        }
      }
    },
    {
      "id": "security-score",
      "type": "gauge",
      "title": "Security Score",
      "description": "Single 0–100 score reflecting the overall vulnerability posture of your organisation.",
      "defaultSize": "1/3",
      "tier": "community",
      "config": {}
    },
    {
      "id": "affected-repos",
      "type": "stat-card",
      "title": "Affected Repositories",
      "description": "Number of repositories with at least one open vulnerability alert.",
      "defaultSize": "1/3",
      "tier": "community",
      "config": {}
    },
    {
      "id": "license-overview",
      "type": "bar-chart",
      "title": "License Distribution",
      "description": "Breakdown of open-source licenses in use across all repositories.",
      "defaultSize": "full",
      "tier": "community",
      "config": {
        "max_licenses": {
          "type": "number",
          "label": "Max licenses to show",
          "default": 10,
          "min": 3,
          "max": 30
        },
        "license_blacklist": {
          "type": "string",
          "label": "Flagged licenses (comma-separated)",
          "default": "",
          "tier": "pro"
        }
      }
    }
  ],
  "defaultDashboard": {
    "name": "Dependencies & Security",
    "layout": [
      { "widgetId": "vuln-summary",     "width": "1/3" },
      { "widgetId": "security-score",   "width": "1/3" },
      { "widgetId": "affected-repos",   "width": "1/3" },
      { "widgetId": "license-overview", "width": "full" }
    ]
  },
  "ui": {
    "navItem": {
      "label": "Security",
      "icon": "⚑",
      "path": "/dependencies",
      "order": 4
    }
  },
  "backend": {
    "syncHooks": ["onSchedule"],
    "syncModule": "plugins.dependencies.sync"
  },
  "license": {
    "required": false
  }
}
